<?xml version="1.0" encoding="UTF-8"?>




<cei xmlns:xsi="http://www.w3.org/2001/XMLSchema-instance" xsi:noNamespaceSchemaLocation="http://www.cei.lmu.de/schema/cei060122.xsd">
		
	<teiHeader>
		<fileDesc>
			<titleStmt>
				<title>Friedrich I. – RI IV,2,4 n. 3157</title>
			</titleStmt>
			<editionStmt>
				<p n="volume">RI IV,2,4 - Friedrich I., 4. Lfg. 1181-1190</p>
				<p n="repository">Regesta Imperii Online: <ref type="external" target="http://www.regesta-imperii.de/cei/004-002-004/sources/1188-05-11_1_0_4_2_4_583_3157"></ref></p>
			</editionStmt>
			<publicationStmt>
				<p n="authority">
					Deutsche Kommission für die Bearbeitung der Regesta Imperii e.V. bei der Akademie der Wissenschaften und der Literatur | Mainz
				</p>
				<publisher>Akademie der Wissenschaften und der Literatur | Mainz – Digitale Akademie</publisher>
				<availability>
					<p>Bereitgestellt unter einer <ref target="https://creativecommons.org/licenses/by/4.0/">Creative Commons Namensnennung (CC BY 4.0)</ref></p>
					<p>Bei Verwendung müssen Sie den Namen des Urhebers und folgenden Link zum Material angeben: <ref type="external" target="http://www.regesta-imperii.de/cei/004-002-004/sources/1188-05-11_1_0_4_2_4_583_3157"></ref></p>
				</availability>
				<date></date>
			</publicationStmt>
			<sourceDesc>
				<bibl>
					<idno n="uri">http://www.regesta-imperii.de/id/1188-05-11_1_0_4_2_4_583_3157</idno>
					<idno n="department">004</idno>
					<idno n="volume">002</idno>
					<idno n="issue">004</idno>
				</bibl>
			</sourceDesc>
		</fileDesc>
		<encodingDesc>
			<geoDecl xml:id="WGS" datum="WGS84">World Geodetic System</geoDecl>
		</encodingDesc>
		<revisionDesc>
			<p>
				
				<date type="creation" n="1339535676" value="2012-06-12"></date>
				<date type="lastmod" n="1340987057" value="2012-06-29"></date>
				
			</p>
		</revisionDesc>
	</teiHeader>

	<charter>
		<chDesc>
			<head>
				<idno>RI IV,2,4 n. 3157</idno>
				<issued>
					<issueDate>
						<p>
							<dateRange from="1188-05-11" to="1188-05-11">1188
									Mai 11</dateRange>
						</p>
					</issueDate>
					
						<issuePlace>
							
									<placeName>in der Thomaskirche zu Weiz</placeName>
								
						</issuePlace>
					
					
				</issued>
				
			</head>
			<relevantPersonal>
				
					<issuer><persName>Friedrich I.</persName></issuer>
				
				
				
				
				
				
			</relevantPersonal>
			
				<abstract><p>Liutold von Gutenberg überträgt dem Kloster Göss vor 								seinem Antritt zum Kreuzzug (Zahn, n<hi rend="sup">o</hi> 688: <hi rend="italic">… Iherosolimam in armis contra inimicos crucis 									Christi proficiscens</hi> …) das Patronatsrecht über die Pfarre 								St. Dionysen (bei Bruck an der Mur) und erhält am selben Tag zur 								Aufbringung der für die Kreuzfahrt erforderlichen Mittel für die 								durch seine Tochter, Äbtissin Ottilie von Göß, durchgeführte 								lehnsrechtliche Vergabe eines Hofes von dem damit Belehnten einen 								Betrag von 70 Mark (Zahn, n<hi rend="sup">o</hi> 689: <hi rend="italic">… profecturus Jherosolimam … septuaginta marcas … 									receperat in sumptus necessarios.</hi>).</p></abstract>
			
			<diplomaticAnalysis>
				
				
				
					<div type="transmission"><p>Zahn, UB. d. Herzogthums Steiermark 1, 671 									n<hi rend="sup">o</hi> 688 und 672 n<hi rend="sup">o</hi> 689.</p></div>
				
				
					<div type="commentary"><p>Vgl. Hiestand, ”precipua tocius christianismi 								columpna”, in: Friedrich Barbarossa (VuF 40, 1992) 86 f. – 								Interessantes Beispiel für die bald nach dem Hoftag Jesu Christi 								aufgenommenen Bemühungen von Kreuzfahrern, die erforderliche 								Finanzierung des Unternehmens, die der Kaiser ja verlangt hatte 								(vgl. Reg. 3145), zu sichern.</p></div>
				
				
			</diplomaticAnalysis>
			
			
			
		</chDesc>
	</charter>

</cei>
		
