<?xml version="1.0" encoding="UTF-8"?>




<cei xmlns:xsi="http://www.w3.org/2001/XMLSchema-instance" xsi:noNamespaceSchemaLocation="http://www.cei.lmu.de/schema/cei060122.xsd">
		
	<teiHeader>
		<fileDesc>
			<titleStmt>
				<title>Friedrich I. – RI IV,2,1 n. 354</title>
			</titleStmt>
			<editionStmt>
				<p n="volume">RI IV,2,1 - Friedrich I., 1. Lfg. 1152 (1122)-1158</p>
				<p n="repository">Regesta Imperii Online: <ref type="external" target="http://www.regesta-imperii.de/cei/004-002-001/sources/1155-09-07_1_0_4_2_1_356_354"></ref></p>
			</editionStmt>
			<publicationStmt>
				<p n="authority">
					Deutsche Kommission für die Bearbeitung der Regesta Imperii e.V. bei der Akademie der Wissenschaften und der Literatur | Mainz
				</p>
				<publisher>Akademie der Wissenschaften und der Literatur | Mainz – Digitale Akademie</publisher>
				<availability>
					<p>Bereitgestellt unter einer <ref target="https://creativecommons.org/licenses/by/4.0/">Creative Commons Namensnennung (CC BY 4.0)</ref></p>
					<p>Bei Verwendung müssen Sie den Namen des Urhebers und folgenden Link zum Material angeben: <ref type="external" target="http://www.regesta-imperii.de/cei/004-002-001/sources/1155-09-07_1_0_4_2_1_356_354"></ref></p>
				</availability>
				<date></date>
			</publicationStmt>
			<sourceDesc>
				<bibl>
					<idno n="uri">http://www.regesta-imperii.de/id/1155-09-07_1_0_4_2_1_356_354</idno>
					<idno n="department">004</idno>
					<idno n="volume">002</idno>
					<idno n="issue">001</idno>
				</bibl>
			</sourceDesc>
		</fileDesc>
		<encodingDesc>
			<geoDecl xml:id="WGS" datum="WGS84">World Geodetic System</geoDecl>
		</encodingDesc>
		<revisionDesc>
			<p>
				
				<date type="creation" n="1339416789" value="2012-06-11"></date>
				<date type="lastmod" n="1426240625" value="2015-03-13"></date>
				
			</p>
		</revisionDesc>
	</teiHeader>

	<charter>
		<chDesc>
			<head>
				<idno>RI IV,2,1 n. 354</idno>
				<issued>
					<issueDate>
						<p>
							<dateRange from="1155-09-07" to="1155-09-07">(1155 wohl kurz vor September 7)</dateRange>
						</p>
					</issueDate>
					
					
				</issued>
				
			</head>
			<relevantPersonal>
				
					<issuer><persName>Friedrich I.</persName></issuer>
				
				
					<recipient><hi rend="spaced">Verona</hi></recipient>
				
				
				
					<scribe>Verfaßt von ZB</scribe>
				
				
				
			</relevantPersonal>
			
				<abstract><p>Friedrich untersagt in einem an die Häupter der Stadt <span sameAs="recipient"><hi rend="spaced">Verona</hi> </span>  (<hi rend="italic">Al[berto] Tince et Ro.</hi>) gerichteten Schreiben jedermann, die Rechte und Freiheiten des Bischofs von Verona, den er in seinen Schutz nimmt, zu verletzen, wobei die Gerichtshoheit, das Einheben von Abgaben und das Aufgebot für das Reich besonders genannt werden, befreit den Bischof vom Kalumnieneid und erlaubt ihm, in seinem Namen anzuordnen, daß über die Übeltäter in seinem Herrschaftsbereich <hi rend="italic">instrumenta</hi>  angelegt werden. - <span n="clerk">Verfaßt von ZB</span>. <span n="incipit"><hi rend="italic">Notum volumus omnibus</hi> </span>.</p></abstract>
			
			<diplomaticAnalysis>
				
				
					<div type="incipit"><p><hi rend="italic">Notum volumus omnibus</hi></p></div>
				
				
					<div type="transmission"><p>Kop.: Abschrift des 18. Jh. in den Processi B 35 n<hi rend="sup">o</hi>  2001 f. 1, Staatsarchiv Verona (C). Drucke: Cipolla, Kaiserurkunden, MIÖG 4 (1883) 224 n<hi rend="sup">o</hi>  1; MG. DF. I. 122. Reg.: Stumpf 4533 a.</p></div>
				
				
					<div type="commentary"><p>Die zeitliche Einordnung ergibt sich aus dem Inhalt, besonders aus der vor den Ereignissen in der Veroneser Klause (Reg. <ref target="http://www.regesta-imperii.de/regesten/4-2-1-friedrich-i/nr/1155-09-00_2_0_4_2_1_358_356.html" type="internal" n="regesten">356</ref>) noch huldvollen Grußformel, und wird durch die Diktatzuweisung gestützt. Zur Person des in der Adresse genannten <hi rend="italic">Ro.</hi>, wahrscheinlich Romanus, vgl. Ludwig, Podestaten (Diss. d. Univ. Wien 90, 1973) 147.</p></div>
				
				
			</diplomaticAnalysis>
			
			
			
				<div type="resources">
					<list><item><ref target="http://regesta-imperii.digitale-sammlungen.de/seite/ri04_opl1980_0117" type="external" n="bsb">Digitalisat der Buchseite</ref></item><item><ref target="http://www.mgh.de/dmgh/diplomata/resolving/D_F_I_122" type="external" n="unkown">Druck in den MGH Diplomata</ref></item></list>
				</div>
			
		</chDesc>
	</charter>

</cei>
		
