<?xml version="1.0" encoding="UTF-8"?>




<cei xmlns:xsi="http://www.w3.org/2001/XMLSchema-instance" xsi:noNamespaceSchemaLocation="http://www.cei.lmu.de/schema/cei060122.xsd">
		
	<teiHeader>
		<fileDesc>
			<titleStmt>
				<title>Friedrich I. – RI IV,2,2 n. 1071</title>
			</titleStmt>
			<editionStmt>
				<p n="volume">RI IV,2,2 - Friedrich I., 2. Lfg. 1158-1168</p>
				<p n="repository">Regesta Imperii Online: <ref type="external" target="http://www.regesta-imperii.de/cei/004-002-002/sources/1162-04-27_1_0_4_2_2_513_1071"></ref></p>
			</editionStmt>
			<publicationStmt>
				<p n="authority">
					Deutsche Kommission für die Bearbeitung der Regesta Imperii e.V. bei der Akademie der Wissenschaften und der Literatur | Mainz
				</p>
				<publisher>Akademie der Wissenschaften und der Literatur | Mainz – Digitale Akademie</publisher>
				<availability>
					<p>Bereitgestellt unter einer <ref target="https://creativecommons.org/licenses/by/4.0/">Creative Commons Namensnennung (CC BY 4.0)</ref></p>
					<p>Bei Verwendung müssen Sie den Namen des Urhebers und folgenden Link zum Material angeben: <ref type="external" target="http://www.regesta-imperii.de/cei/004-002-002/sources/1162-04-27_1_0_4_2_2_513_1071"></ref></p>
				</availability>
				<date></date>
			</publicationStmt>
			<sourceDesc>
				<bibl>
					<idno n="uri">http://www.regesta-imperii.de/id/1162-04-27_1_0_4_2_2_513_1071</idno>
					<idno n="department">004</idno>
					<idno n="volume">002</idno>
					<idno n="issue">002</idno>
				</bibl>
			</sourceDesc>
		</fileDesc>
		<encodingDesc>
			<geoDecl xml:id="WGS" datum="WGS84">World Geodetic System</geoDecl>
		</encodingDesc>
		<revisionDesc>
			<p>
				
				<date type="creation" n="1339417607" value="2012-06-11"></date>
				<date type="lastmod" n="1426244201" value="2015-03-13"></date>
				
			</p>
		</revisionDesc>
	</teiHeader>

	<charter>
		<chDesc>
			<head>
				<idno>RI IV,2,2 n. 1071</idno>
				<issued>
					<issueDate>
						<p>
							<dateRange from="1162-04-27" to="1162-04-27">1162 April 27</dateRange>
						</p>
					</issueDate>
					
						<issuePlace>
							
									
										
												<placeName key="Pavia">Pavia</placeName>
												<location><geo decls="#WGS">45.1167, 9.1333</geo></location>
											
									
								
						</issuePlace>
					
					
						<dateOrig>(V kal. madii, Papie post destructionem Mediolani)</dateOrig>
					
				</issued>
				
			</head>
			<relevantPersonal>
				
					<issuer><persName>Friedrich I.</persName></issuer>
				
				
					<recipient><hi rend="spaced">Civate</hi></recipient>
				
				
					<notarius function="chancellor"><hi rend="italic">Vdalricus canc. vice Reinaldi Coloniensis archiep. et archicanc. </hi></notarius>
				
				
					<scribe>geschrieben und wohl auch verfaßt von RC (Anklänge an das Diktat des RG)</scribe>
				
				
					<testis function="witnesses">die Erzbischöfe Rainald von Köln und Heraclius von Lyon, die Bischöfe Heinrich von Lüttich, Ortlieb von Basel und Hermann von Konstanz, Herzog Friedrich von Schwaben, Pfalzgraf Konrad bei Rhein, die Markgrafen Otto (von Meißen), Dietrich (von der Lausitz) und Albert (von Sachsen), die Grafen Dedo (von Groitzsch), Rudolf von Pfullendorf und Ulrich von Lenzburg, Markgraf Wilhelm von Montferrat, Graf Wido von Biandrate, Herzog Ulrich (von Böhmen), Graf Markward von Grumbach, Graf Gebhard von Leuchtenberg und sein Bruder Markward, Ulrich von Herrlingen</testis>
				
				
			</relevantPersonal>
			
				<abstract><p>Friedrich nimmt die Reichsabtei <span sameAs="recipient"><hi rend="spaced">Civate</hi> </span>  unter ihrem besonders in den Kämpfen gegen Mailand um das Reich hochverdienten Abt Algisus in seinen Schutz, bestätigt ihr die genannten Besitzungen und befreit sie von allen Abgaben außer denen an das Reich. <span n="witnesses">Z.: die Erzbischöfe Rainald von Köln und Heraclius von Lyon, die Bischöfe Heinrich von Lüttich, Ortlieb von Basel und Hermann von Konstanz, Herzog Friedrich von Schwaben, Pfalzgraf Konrad bei Rhein, die Markgrafen Otto (von Meißen), Dietrich (von der Lausitz) und Albert (von Sachsen), die Grafen Dedo (von Groitzsch), Rudolf von Pfullendorf und Ulrich von Lenzburg, Markgraf Wilhelm von Montferrat, Graf Wido von Biandrate, Herzog Ulrich (von Böhmen), Graf Markward von Grumbach, Graf Gebhard von Leuchtenberg und sein Bruder Markward, Ulrich von Herrlingen</span>. - <span n="chancellor"><hi rend="italic">Vdalricus canc. vice Reinaldi Coloniensis archiep. et archicanc. </hi> </span>; <span n="clerk">geschrieben und wohl auch verfaßt von RC (Anklänge an das Diktat des RG)</span>. <span n="incipit"><hi rend="italic">Cum ad promovendum</hi> </span>.</p></abstract>
			
			<diplomaticAnalysis>
				
				
					<div type="incipit"><p><hi rend="italic">Cum ad promovendum</hi></p></div>
				
				
					<div type="transmission"><p>Kop.: Abschrift aus dem Beginn des 14. Jh., Archiv des Domkapitels Pisa (B). Drucke: Bognetti - Marcora, L'abbazia benedettina di Civate 144; MG. DF. I. 359. Faks.: Bognetti - Marcora, a. a. O. 140. Reg.: Wauters, Table chronol. 7/1, 282; Stumpf 3941.</p></div>
				
				
				
			</diplomaticAnalysis>
			
			
			
				<div type="resources">
					<list><item><ref target="http://regesta-imperii.digitale-sammlungen.de/seite/ri04_opl1991_0142" type="external" n="bsb">Digitalisat der Buchseite</ref></item><item><ref target="http://www.mgh.de/dmgh/diplomata/resolving/D_F_I_359" type="external" n="unkown">Druck in den MGH Diplomata</ref></item></list>
				</div>
			
		</chDesc>
	</charter>

</cei>
		
