<?xml version="1.0" encoding="UTF-8"?>




<cei xmlns:xsi="http://www.w3.org/2001/XMLSchema-instance" xsi:noNamespaceSchemaLocation="http://www.cei.lmu.de/schema/cei060122.xsd">
		
	<teiHeader>
		<fileDesc>
			<titleStmt>
				<title>Friedrich I. – RI IV,2,2 n. 1112</title>
			</titleStmt>
			<editionStmt>
				<p n="volume">RI IV,2,2 - Friedrich I., 2. Lfg. 1158-1168</p>
				<p n="repository">Regesta Imperii Online: <ref type="external" target="http://www.regesta-imperii.de/cei/004-002-002/sources/1162-07-24_1_0_4_2_2_554_1112"></ref></p>
			</editionStmt>
			<publicationStmt>
				<p n="authority">
					Deutsche Kommission für die Bearbeitung der Regesta Imperii e.V. bei der Akademie der Wissenschaften und der Literatur | Mainz
				</p>
				<publisher>Akademie der Wissenschaften und der Literatur | Mainz – Digitale Akademie</publisher>
				<availability>
					<p>Bereitgestellt unter einer <ref target="https://creativecommons.org/licenses/by/4.0/">Creative Commons Namensnennung (CC BY 4.0)</ref></p>
					<p>Bei Verwendung müssen Sie den Namen des Urhebers und folgenden Link zum Material angeben: <ref type="external" target="http://www.regesta-imperii.de/cei/004-002-002/sources/1162-07-24_1_0_4_2_2_554_1112"></ref></p>
				</availability>
				<date></date>
			</publicationStmt>
			<sourceDesc>
				<bibl>
					<idno n="uri">http://www.regesta-imperii.de/id/1162-07-24_1_0_4_2_2_554_1112</idno>
					<idno n="department">004</idno>
					<idno n="volume">002</idno>
					<idno n="issue">002</idno>
				</bibl>
			</sourceDesc>
		</fileDesc>
		<encodingDesc>
			<geoDecl xml:id="WGS" datum="WGS84">World Geodetic System</geoDecl>
		</encodingDesc>
		<revisionDesc>
			<p>
				
				<date type="creation" n="1339417607" value="2012-06-11"></date>
				<date type="lastmod" n="1426244751" value="2015-03-13"></date>
				
			</p>
		</revisionDesc>
	</teiHeader>

	<charter>
		<chDesc>
			<head>
				<idno>RI IV,2,2 n. 1112</idno>
				<issued>
					<issueDate>
						<p>
							<dateRange from="1162-07-24" to="1162-07-24">1162 Juli 24</dateRange>
						</p>
					</issueDate>
					
						<issuePlace>
							
									
										
												<placeName key="Parma">Parma</placeName>
												<location><geo decls="#WGS">44.7, 10.0833</geo></location>
											
									
								
						</issuePlace>
					
					
						<dateOrig>(nono kall. aug., Parme in Parmensi palatio)</dateOrig>
					
				</issued>
				
			</head>
			<relevantPersonal>
				
					<issuer><persName>Friedrich I.</persName></issuer>
				
				
					<recipient><hi rend="spaced">Bauhütte des Domes zu Parma</hi></recipient>
				
				
				
				
					<testis function="witnesses">Bischof Aicard von Parma, Pfalzgraf Otto (von Wittelsbach), Castellanus, der Dolmetsch des Kaisers, Azo, der Regalienverwalter des Kaisers, Vetulus, der Sachwalter und Beisitzer der Podestà von Parma</testis>
				
				
			</relevantPersonal>
			
				<abstract><p>Friedrich schenkt der <span sameAs="recipient"><hi rend="spaced">Bauhütte des Domes zu Parma</hi> </span>  den Zehent des Sumpflandes und der übrigen Regalien des Bistums, der ihr vom verstorbenen Bischof Bernhard übertragen worden ist, und investiert damit ihren Dienstmann Marrauo. <span n="witnesses">Z.: Bischof Aicard von Parma, Pfalzgraf Otto (von Wittelsbach), Castellanus, der Dolmetsch des Kaisers, Azo, der Regalienverwalter des Kaisers, Vetulus, der Sachwalter und Beisitzer der Podestà von Parma</span>. - <hi rend="italic">Ego Iohannes Calandinus imperialis sacri palacii notarius et Parmensis episcopi L(anfranci) interfui et iussione domini imperatoris F(rederici) scripsi, corroboravi, complevi et dedi</hi>; italienisches Notariatsinstrument. <span n="incipit"><hi rend="italic">Quisquis in sanctis</hi> </span>.</p></abstract>
			
			<diplomaticAnalysis>
				
				
					<div type="incipit"><p><hi rend="italic">Quisquis in sanctis</hi></p></div>
				
				
					<div type="transmission"><p>Orig.: Staatsarchiv Parma (A). Druck: MG. DF. I. 376. Reg.: Stumpf 3959.</p></div>
				
				
					<div type="commentary"><p>Zur Überlieferung vgl. die Vorbemerkung des D. - Interessant sind hier die Nennungen des Dolmetsch und des <hi rend="italic">minister regalium</hi>  des Kaisers in der Zeugenreihe. - Zu der in der Datierung erwähnten Pfalz, bei der es sich auch um die des Bischofs handeln könnte, vgl. Opll, Itinerar, 117 f. mit Anm. 52.</p></div>
				
				
			</diplomaticAnalysis>
			
			
			
				<div type="resources">
					<list><item><ref target="http://regesta-imperii.digitale-sammlungen.de/seite/ri04_opl1991_0154" type="external" n="bsb">Digitalisat der Buchseite</ref></item><item><ref target="http://www.mgh.de/dmgh/diplomata/resolving/D_F_I_376" type="external" n="unkown">Druck in den MGH Diplomata</ref></item></list>
				</div>
			
		</chDesc>
	</charter>

</cei>
		
