<?xml version="1.0" encoding="UTF-8"?>




<cei xmlns:xsi="http://www.w3.org/2001/XMLSchema-instance" xsi:noNamespaceSchemaLocation="http://www.cei.lmu.de/schema/cei060122.xsd">
		
	<teiHeader>
		<fileDesc>
			<titleStmt>
				<title>Friedrich I. – RI IV,2,3 n. 2362</title>
			</titleStmt>
			<editionStmt>
				<p n="volume">RI IV,2,3 - Friedrich I., 3. Lfg. 1168-1180</p>
				<p n="repository">Regesta Imperii Online: <ref type="external" target="http://www.regesta-imperii.de/cei/004-002-003/sources/1177-12-20_1_0_4_2_3_590_2362"></ref></p>
			</editionStmt>
			<publicationStmt>
				<p n="authority">
					Deutsche Kommission für die Bearbeitung der Regesta Imperii e.V. bei der Akademie der Wissenschaften und der Literatur | Mainz
				</p>
				<publisher>Akademie der Wissenschaften und der Literatur | Mainz – Digitale Akademie</publisher>
				<availability>
					<p>Bereitgestellt unter einer <ref target="https://creativecommons.org/licenses/by/4.0/">Creative Commons Namensnennung (CC BY 4.0)</ref></p>
					<p>Bei Verwendung müssen Sie den Namen des Urhebers und folgenden Link zum Material angeben: <ref type="external" target="http://www.regesta-imperii.de/cei/004-002-003/sources/1177-12-20_1_0_4_2_3_590_2362"></ref></p>
				</availability>
				<date></date>
			</publicationStmt>
			<sourceDesc>
				<bibl>
					<idno n="uri">http://www.regesta-imperii.de/id/1177-12-20_1_0_4_2_3_590_2362</idno>
					<idno n="department">004</idno>
					<idno n="volume">002</idno>
					<idno n="issue">003</idno>
				</bibl>
			</sourceDesc>
		</fileDesc>
		<encodingDesc>
			<geoDecl xml:id="WGS" datum="WGS84">World Geodetic System</geoDecl>
		</encodingDesc>
		<revisionDesc>
			<p>
				
				<date type="creation" n="1339420657" value="2012-06-11"></date>
				<date type="lastmod" n="1430901856" value="2015-05-06"></date>
				
			</p>
		</revisionDesc>
	</teiHeader>

	<charter>
		<chDesc>
			<head>
				<idno>RI IV,2,3 n. 2362</idno>
				<issued>
					<issueDate>
						<p>
							<dateRange from="1177-12-20" to="1177-12-20">1177 Dezember 20  — 1178 Januar 1</dateRange>
						</p>
					</issueDate>
					
						<issuePlace>
							
									<placeName>Assisi, —</placeName>
								
						</issuePlace>
					
					
						<dateOrig><hi rend="italic">(kal. ianuariis, apud Assisum)</hi></dateOrig>
					
				</issued>
				
			</head>
			<relevantPersonal>
				
					<issuer><persName>Friedrich I.</persName></issuer>
				
				
				
				
					<scribe>Wohl außerhalb der Kanzlei verfaßt</scribe>
				
				
					<testis function="witnesses">Erzbischof Christian von Mainz, Bischof Konrad von Worms, Protonotar Wortwin, Ugolinus Bonicomitis, Simplicianus, Ugo <hi rend="italic">de Aspramonte</hi>  und Egidius von Montefiore</testis>
				
				
			</relevantPersonal>
			
				<abstract><p>Friedrich sieht den <hi rend="spaced">Bewohnern von Fermo</hi>  ihre Unbotmäßigkeit nach und gestattet ihnen, sich wieder in ihrer Stadt anzusiedeln, bestätigt ihnen die Freiheit, den alten Rechtszustand und die Gewohnheitsrechte inner- und außerhalb ihrer Stadt, wie sie sie ein Jahr vor der Zerstörung Fermos durch das Heer (Erzbischof Christians) von Mainz innehatten, und erläßt ihnen zur Schadensminderung alle Abgaben und das Fodrum für die Dauer von zehn Jahren. <span n="witnesses">Z.: Erzbischof Christian von Mainz, Bischof Konrad von Worms, Protonotar Wortwin, Ugolinus Bonicomitis, Simplicianus, Ugo <hi rend="italic">de Aspramonte</hi>  und Egidius von Montefiore</span>. — <span n="clerk">Wohl außerhalb der Kanzlei verfaßt</span>. <span n="incipit"><hi rend="italic">Omnibus Romani imperii</hi> </span>.</p></abstract>
			
			<diplomaticAnalysis>
				
				
					<div type="incipit"><p><hi rend="italic">Omnibus Romani imperii</hi></p></div>
				
				
					<div type="transmission"><p>Kop.: Transsumpt Kaiser Friedrichs II. von 1242 August (B.-Ficker 3314) in der Sezione dell;Archivio di Stato zu Fermo, Archivio diplomatico comunale (B); beschädigte Abschrift des 13. Jh. im Liber episcopatus von Fermo (cod. 1030) f. 121', ebenda (C). Drucke: Stumpf, Acta ined. 692 n<hi rend="sup">o</hi>  493; MG.DF.I.724. Regg.: Acht, Mainzer UB. 2/2, 658 n<hi rend="sup">o</hi>  404; Stumpf 4239.</p></div>
				
				
					<div type="commentary"><p>Wohl uneinheitliche Datierung, vgl. dazu die Vorbemerkung zum D. — Zur Vorgeschichte vgl. auch Regg. <ref type="unmatched">2197, 2223</ref>  und <ref target="http://www.regesta-imperii.de/regesten/4-2-3-friedrich-i/nr/1177-02-00_2_0_4_2_3_467_2239.html" type="internal" n="regesten">2239</ref>  sowie Opll, Stadt und Reich, 266 f.</p></div>
				
				
			</diplomaticAnalysis>
			
			
			
				<div type="resources">
					<list><item><ref target="http://regesta-imperii.digitale-sammlungen.de/seite/ri04_opl2001_0210" type="external" n="bsb">Digitalisat der Buchseite</ref></item><item><ref target="http://www.mgh.de/dmgh/diplomata/resolving/D_F_I_724" type="external" n="unkown">Druck in den MGH Diplomata</ref></item></list>
				</div>
			
		</chDesc>
	</charter>

</cei>
		
